{
  "2955fb87-6ecc-41b3-b79a-cff740290188.jpg": {
    "fileref": "",
    "size": 19061,
    "filename": "2955fb87-6ecc-41b3-b79a-cff740290188.jpg",
    "base64_img_data": "",
    "file_attributes": {},
    "regions": {
      "0": {
        "shape_attributes": {
          "name": "polygon",
          "all_points_x": [
            125.93548387096774,
            154.32258064516128,
            177.54838709677418,
            187.8709677419355,
            189.93548387096774,
            256,
            256,
            223.48387096774192,
            145.54838709677418,
            153.29032258064515,
            125.93548387096774
          ],
          "all_points_y": [
            50.064516129032256,
            0,
            0,
            5.161290322580645,
            0,
            38.193548387096776,
            74.32258064516128,
            125.93548387096774,
            79.48387096774194,
            67.09677419354838,
            50.064516129032256
          ]
        },
        "region_attributes": {
          "label": "roof"
        }
      },
      "1": {
        "shape_attributes": {
          "name": "polygon",
          "all_points_x": [
            85.16129032258064,
            117.16129032258064,
            50.064516129032256,
            52.12903225806451,
            59.87096774193548,
            66.58064516129032,
            73.29032258064515,
            81.03225806451613,
            85.16129032258064
          ],
          "all_points_y": [
            241.03225806451613,
            256,
            256,
            245.6774193548387,
            240.51612903225805,
            228.1290322580645,
            228.1290322580645,
            233.29032258064515,
            241.03225806451613
          ]
        },
        "region_attributes": {
          "label": "pool"
        }
      }
    }
  }
}